bact_device_models/__init__.py
bact_device_models/devices/__init__.py
bact_device_models/devices/bpm_elem.py
bact_device_models/devices/bpm_elem_libera.py
bact_device_models/filters/__init__.py
bact_device_models/filters/bpm_calibration.py
bact_device_models-0.1.0.dist-info/LICENSE
bact_device_models-0.1.0.dist-info/METADATA
bact_device_models-0.1.0.dist-info/WHEEL
bact_device_models-0.1.0.dist-info/RECORD
